tf_frodo/__init__.py
tf_frodo/frodo.py
tf_frodo/test_model.py
tf_frodo/utils.py
tf_frodo-0.0.3.dist-info/LICENSE
tf_frodo-0.0.3.dist-info/METADATA
tf_frodo-0.0.3.dist-info/WHEEL
tf_frodo-0.0.3.dist-info/top_level.txt
tf_frodo-0.0.3.dist-info/RECORD
