Metadata-Version: 2.1
Name: tf-frodo
Version: 0.0.3
Summary: FRODO for free rejection of out-of-distribution samples in deep learning
Home-page: https://github.com/xarion/tf_frodo.git
Author: Erdi Calli
Author-email: erdicalli@gmail.com
License: UNKNOWN
Platform: UNKNOWN
Classifier: Programming Language :: Python :: 3
Classifier: License :: OSI Approved :: MIT License
Classifier: Operating System :: OS Independent
Requires-Python: >=3.6
License-File: LICENSE
